heurist/__init__.py
heurist/api/__init__.py
heurist/api/client.py
heurist/api/connection.py
heurist/api/constants.py
heurist/api/credentials.py
heurist/api/exceptions.py
heurist/api/url_builder.py
heurist/api/utils.py
heurist/cli/__init__.py
heurist/cli/__main__.py
heurist/cli/load.py
heurist/cli/parse_log.py
heurist/cli/records.py
heurist/cli/schema.py
heurist/database/__init__.py
heurist/database/basedb.py
heurist/database/database.py
heurist/log/__init__.py
heurist/log/constants.py
heurist/log/iterator.py
heurist/log/model.py
heurist/log/summary.py
heurist/models/__init__.py
heurist/models/dynamic/__init__.py
heurist/models/dynamic/annotation.py
heurist/models/dynamic/create_model.py
heurist/models/dynamic/date.py
heurist/models/dynamic/type.py
heurist/models/structural/DetailTypes.py
heurist/models/structural/RecStructure.py
heurist/models/structural/RecTypeGroups.py
heurist/models/structural/RecTypes.py
heurist/models/structural/Terms.py
heurist/models/structural/__init__.py
heurist/models/structural/dty.py
heurist/models/structural/hml_structure.py
heurist/models/structural/rst.py
heurist/models/structural/rtg.py
heurist/models/structural/rty.py
heurist/models/structural/trm.py
heurist/models/structural/utils.py
heurist/schema/__init__.py
heurist/schema/models.py
heurist/schema/rel_to_dict.py
heurist/sql/__init__.py
heurist/sql/joinRecordTypeIDNameByGroupType.sql
heurist/sql/joinRecordTypeMetadata.sql
heurist/sql/selectRecordTypeSchema.sql
heurist/sql/sql_safety.py
heurist/utils/constants.py
heurist/utils/rel_to_dict_array.py
heurist/validators/__init__.py
heurist/validators/detail_validator.py
heurist/validators/exceptions.py
heurist/validators/parse_heurist_date.py
heurist/validators/record_validator.py
heurist/workflows/__init__.py
heurist/workflows/etl.py
mock_data/__init__.py
mock_data/blocktext/__init__.py
mock_data/blocktext/single.py
mock_data/date/__init__.py
mock_data/date/compound_repeated.py
mock_data/date/compound_single.py
heurist_api-0.2.8.dist-info/METADATA
heurist_api-0.2.8.dist-info/WHEEL
heurist_api-0.2.8.dist-info/entry_points.txt
heurist_api-0.2.8.dist-info/licenses/LICENSE
heurist_api-0.2.8.dist-info/RECORD
