Metadata-Version: 2.4
Name: heurist-api
Version: 0.2.8
Dynamic: Summary
Project-URL: Homepage, https://lostma-erc.github.io/heurist-api/
Project-URL: Documentation, https://lostma-erc.github.io/heurist-api/
Project-URL: Repository, https://github.com/LostMa-ERC/heurist-api
Project-URL: Issues, https://github.com/LostMa-ERC/heurist-api/issues
Author-email: Kelly Christensen <kelly.christensen@chartes.psl.eu>, Virgile Reignier <virgile.reignier@chartes.psl.eu>
License: Attribution-ShareAlike 4.0 International
License-File: LICENSE
Keywords: duckdb,etl
Requires-Python: >=3.10
Requires-Dist: click>=8.2.0
Requires-Dist: duckdb>=1.2.2
Requires-Dist: lxml>=5.4.0
Requires-Dist: pandas>=2.2.3
Requires-Dist: polars>=1.29.0
Requires-Dist: pyarrow>=20.0.0
Requires-Dist: pydantic-xml<2.17.0,>=2.16.0
Requires-Dist: pydantic>=2.11.4
Requires-Dist: python-dotenv>=1.1.0
Requires-Dist: requests>=2.32.3
Requires-Dist: rich>=14.0.0
Requires-Dist: tenacity>=9.1.2
Provides-Extra: dev
Requires-Dist: coverage>=7.8.0; extra == 'dev'
Requires-Dist: genbadge[coverage]>=1.1.2; extra == 'dev'
Requires-Dist: isort>=6.0.1; extra == 'dev'
Requires-Dist: mkdocs-gen-files>=0.5.0; extra == 'dev'
Requires-Dist: mkdocs-literate-nav>=0.6.2; extra == 'dev'
Requires-Dist: mkdocs-material[imaging]>=9.6.14; extra == 'dev'
Requires-Dist: mkdocs>=1.6.1; extra == 'dev'
Requires-Dist: mkdocstrings-python>=1.16.10; extra == 'dev'
Requires-Dist: pre-commit>=4.2.0; extra == 'dev'
Requires-Dist: pymdown-extensions>=10.15; extra == 'dev'
Requires-Dist: pytest>=8.3.5; extra == 'dev'
Requires-Dist: ruff>=0.11.10; extra == 'dev'
Requires-Dist: uv>=0.7.5; extra == 'dev'
